{
  "id": "polycam_scan",
  "name": "Polycam Scan",
  "floor_area_m2": 84.22,
  "bounds": {
    "min": [
      -4.42,
      -17.46,
      0.0
    ],
    "max": [
      4.52,
      17.36,
      3.69
    ]
  },
  "rooms": [
    {
      "id": "room_0",
      "label": "Other",
      "priority": "medium",
      "bounds": {
        "min": [
          -3.9223607,
          -5.413675,
          0.0
        ],
        "max": [
          3.97236,
          -1.8795697,
          3.0
        ]
      }
    },
    {
      "id": "room_1",
      "label": "Other",
      "priority": "medium",
      "bounds": {
        "min": [
          -0.62902769,
          -1.8795697,
          0.0
        ],
        "max": [
          0.83083125,
          8.51157,
          3.0
        ]
      }
    },
    {
      "id": "room_2",
      "label": "Other",
      "priority": "medium",
      "bounds": {
        "min": [
          -0.6290283,
          -16.909955,
          0.0
        ],
        "max": [
          1.5894965,
          -5.413675,
          3.0
        ]
      }
    },
    {
      "id": "room_3",
      "label": "Other",
      "priority": "medium",
      "bounds": {
        "min": [
          -0.62902769,
          8.51157,
          0.0
        ],
        "max": [
          2.2488816,
          14.733961,
          3.0
        ]
      }
    }
  ],
  "walls": [
    {
      "id": "wall_1",
      "from": [
        1.6394966,
        -5.463675
      ],
      "to": [
        4.02236,
        -5.463675
      ],
      "height": 3.69
    },
    {
      "id": "wall_15",
      "from": [
        1.5394965,
        -5.363675
      ],
      "to": [
        3.9223598,
        -5.363675
      ],
      "height": 3.69
    },
    {
      "id": "wall_16",
      "from": [
        1.5394965,
        -5.413675
      ],
      "to": [
        4.02236,
        -5.413675
      ],
      "height": 3.69
    },
    {
      "id": "wall_45",
      "from": [
        -0.6790277,
        14.424498
      ],
      "to": [
        -0.48167456,
        14.424498
      ],
      "height": 3.2
    },
    {
      "id": "wall_17",
      "from": [
        -0.5790277,
        14.324497
      ],
      "to": [
        -0.38167454,
        14.324497
      ],
      "height": 3.2
    },
    {
      "id": "wall_18",
      "from": [
        -0.6790277,
        14.3744975
      ],
      "to": [
        -0.38167454,
        14.3744975
      ],
      "height": 3.2
    },
    {
      "id": "wall_2",
      "from": [
        0.8808312,
        -1.8295708
      ],
      "to": [
        0.8808312,
        8.46157
      ],
      "height": 3.2
    },
    {
      "id": "wall_19",
      "from": [
        0.7808312,
        -1.9295708
      ],
      "to": [
        0.7808312,
        8.56157
      ],
      "height": 3.2
    },
    {
      "id": "wall_20",
      "from": [
        0.8308312,
        -1.9295708
      ],
      "to": [
        0.8308312,
        8.56157
      ],
      "height": 3.2
    },
    {
      "id": "wall_3",
      "from": [
        0.8808312,
        8.46157
      ],
      "to": [
        2.2988816,
        8.46157
      ],
      "height": 3.2
    },
    {
      "id": "wall_21",
      "from": [
        0.7808312,
        8.56157
      ],
      "to": [
        2.1988815,
        8.56157
      ],
      "height": 3.2
    },
    {
      "id": "wall_22",
      "from": [
        0.7808312,
        8.511569999999999
      ],
      "to": [
        2.2988816,
        8.511569999999999
      ],
      "height": 3.2
    },
    {
      "id": "wall_4",
      "from": [
        1.7005978,
        14.783961
      ],
      "to": [
        2.2988816,
        14.783961
      ],
      "height": 3.2
    },
    {
      "id": "wall_23",
      "from": [
        1.7005978,
        14.683962
      ],
      "to": [
        2.1988815,
        14.683962
      ],
      "height": 3.2
    },
    {
      "id": "wall_24",
      "from": [
        1.7005978,
        14.7339615
      ],
      "to": [
        2.2988816,
        14.7339615
      ],
      "height": 3.2
    },
    {
      "id": "wall_5",
      "from": [
        -0.48167456,
        14.424498
      ],
      "to": [
        -0.48167456,
        16.859955
      ],
      "height": 3.2
    },
    {
      "id": "wall_25",
      "from": [
        -0.38167454,
        14.324497
      ],
      "to": [
        -0.38167454,
        16.859955
      ],
      "height": 3.2
    },
    {
      "id": "wall_26",
      "from": [
        -0.43167455,
        14.324497
      ],
      "to": [
        -0.43167455,
        16.859955
      ],
      "height": 3.2
    },
    {
      "id": "wall_6",
      "from": [
        -1.314791,
        -16.959956
      ],
      "to": [
        1.6394966,
        -16.959956
      ],
      "height": 3.2
    },
    {
      "id": "wall_27",
      "from": [
        -1.314791,
        -16.859955
      ],
      "to": [
        1.5394965,
        -16.859955
      ],
      "height": 3.2
    },
    {
      "id": "wall_28",
      "from": [
        -1.314791,
        -16.9099555
      ],
      "to": [
        1.6394966,
        -16.9099555
      ],
      "height": 3.2
    },
    {
      "id": "wall_7",
      "from": [
        -0.6790277,
        -1.8295697
      ],
      "to": [
        -0.6790277,
        14.424498
      ],
      "height": 3.2
    },
    {
      "id": "wall_29",
      "from": [
        -0.5790277,
        -1.9295696
      ],
      "to": [
        -0.5790277,
        14.324497
      ],
      "height": 3.2
    },
    {
      "id": "wall_30",
      "from": [
        -0.6290277,
        -1.9295696
      ],
      "to": [
        -0.6290277,
        14.424498
      ],
      "height": 3.2
    },
    {
      "id": "wall_8",
      "from": [
        2.2988816,
        8.46157
      ],
      "to": [
        2.2988816,
        14.783961
      ],
      "height": 3.2
    },
    {
      "id": "wall_31",
      "from": [
        2.1988815,
        8.56157
      ],
      "to": [
        2.1988815,
        14.683962
      ],
      "height": 3.2
    },
    {
      "id": "wall_32",
      "from": [
        2.24888155,
        8.46157
      ],
      "to": [
        2.24888155,
        14.783961
      ],
      "height": 3.2
    },
    {
      "id": "wall_9",
      "from": [
        1.6394966,
        -16.959956
      ],
      "to": [
        1.6394966,
        -5.463675
      ],
      "height": 3.5
    },
    {
      "id": "wall_33",
      "from": [
        1.5394965,
        -16.859955
      ],
      "to": [
        1.5394965,
        -5.363675
      ],
      "height": 3.5
    },
    {
      "id": "wall_34",
      "from": [
        1.58949655,
        -16.959956
      ],
      "to": [
        1.58949655,
        -5.363675
      ],
      "height": 3.5
    },
    {
      "id": "wall_10",
      "from": [
        0.8808312,
        -1.8295708
      ],
      "to": [
        4.02236,
        -1.8295708
      ],
      "height": 3.69
    },
    {
      "id": "wall_35",
      "from": [
        0.7808312,
        -1.9295708
      ],
      "to": [
        3.9223598,
        -1.9295708
      ],
      "height": 3.69
    },
    {
      "id": "wall_36",
      "from": [
        0.7808312,
        -1.8795708
      ],
      "to": [
        4.02236,
        -1.8795708
      ],
      "height": 3.69
    },
    {
      "id": "wall_11",
      "from": [
        4.02236,
        -5.463675
      ],
      "to": [
        4.02236,
        -1.8295708
      ],
      "height": 3.69
    },
    {
      "id": "wall_37",
      "from": [
        3.9223598,
        -5.363675
      ],
      "to": [
        3.9223598,
        -1.9295708
      ],
      "height": 3.69
    },
    {
      "id": "wall_38",
      "from": [
        3.9723599,
        -5.463675
      ],
      "to": [
        3.9723599,
        -1.8295708
      ],
      "height": 3.69
    },
    {
      "id": "wall_12",
      "from": [
        -0.67902836,
        -15.390214
      ],
      "to": [
        -0.67902836,
        -4.7974855
      ],
      "height": 3.2
    },
    {
      "id": "wall_39",
      "from": [
        -0.57902839,
        -15.390214
      ],
      "to": [
        -0.57902839,
        -4.6974856
      ],
      "height": 3.2
    },
    {
      "id": "wall_40",
      "from": [
        -0.629028375,
        -15.390214
      ],
      "to": [
        -0.629028375,
        -4.6974856
      ],
      "height": 3.2
    },
    {
      "id": "wall_13",
      "from": [
        -3.6650456,
        -4.7974855
      ],
      "to": [
        -0.67902836,
        -4.7974855
      ],
      "height": 3.2
    },
    {
      "id": "wall_41",
      "from": [
        -3.6650456,
        -4.6974856
      ],
      "to": [
        -0.57902839,
        -4.6974856
      ],
      "height": 3.2
    },
    {
      "id": "wall_42",
      "from": [
        -3.6650456,
        -4.74748555
      ],
      "to": [
        -0.57902839,
        -4.74748555
      ],
      "height": 3.2
    },
    {
      "id": "wall_14",
      "from": [
        -3.9223607,
        -1.8295697
      ],
      "to": [
        -0.6790277,
        -1.8295697
      ],
      "height": 3.2
    },
    {
      "id": "wall_43",
      "from": [
        -3.9223607,
        -1.9295696
      ],
      "to": [
        -0.5790277,
        -1.9295696
      ],
      "height": 3.2
    },
    {
      "id": "wall_44",
      "from": [
        -3.9223607,
        -1.87956965
      ],
      "to": [
        -0.5790277,
        -1.87956965
      ],
      "height": 3.2
    }
  ],
  "entry_points": [
    {
      "id": "door_0",
      "label": "Door 1",
      "type": "door",
      "position": [
        -0.628,
        5.183,
        1.0
      ],
      "normal": [
        -1.0,
        0.0,
        0.0
      ],
      "width": 0.94,
      "threat_weight": 1.0
    },
    {
      "id": "door_1",
      "label": "Door 2",
      "type": "door",
      "position": [
        -2.408,
        -4.746,
        1.0
      ],
      "normal": [
        -0.0,
        1.0,
        0.0
      ],
      "width": 1.01,
      "threat_weight": 1.0
    },
    {
      "id": "door_2",
      "label": "Door 3",
      "type": "door",
      "position": [
        2.248,
        14.083,
        1.0
      ],
      "normal": [
        -1.0,
        0.0,
        0.0
      ],
      "width": 0.96,
      "threat_weight": 1.0
    },
    {
      "id": "door_3",
      "label": "Door 4",
      "type": "door",
      "position": [
        -0.822,
        -16.909,
        1.0
      ],
      "normal": [
        -0.0,
        1.0,
        0.0
      ],
      "width": 0.89,
      "threat_weight": 1.0
    },
    {
      "id": "door_4",
      "label": "Door 5",
      "type": "door",
      "position": [
        1.588,
        -8.302,
        1.0
      ],
      "normal": [
        -1.0,
        0.0,
        0.0
      ],
      "width": 0.72,
      "threat_weight": 1.0
    },
    {
      "id": "door_5",
      "label": "Door 6",
      "type": "door",
      "position": [
        0.83,
        5.576,
        1.0
      ],
      "normal": [
        -1.0,
        0.0,
        0.0
      ],
      "width": 1.99,
      "threat_weight": 1.0
    },
    {
      "id": "door_6",
      "label": "Door 7",
      "type": "door",
      "position": [
        1.588,
        -13.811,
        1.0
      ],
      "normal": [
        -1.0,
        0.0,
        0.0
      ],
      "width": 0.87,
      "threat_weight": 1.0
    },
    {
      "id": "door_7",
      "label": "Door 8",
      "type": "door",
      "position": [
        2.248,
        9.095,
        1.0
      ],
      "normal": [
        -1.0,
        0.0,
        0.0
      ],
      "width": 0.93,
      "threat_weight": 1.0
    }
  ],
  "obstructions": [
    {
      "id": "table_other_rect0",
      "label": "Table",
      "category": "table",
      "bounds": {
        "min": [
          0.903,
          -13.182,
          0.099
        ],
        "max": [
          1.539,
          -12.15,
          0.622
        ]
      }
    },
    {
      "id": "chair_dining_four_back_no0",
      "label": "Chair",
      "category": "chair",
      "bounds": {
        "min": [
          1.589,
          11.779,
          0.099
        ],
        "max": [
          2.152,
          12.226,
          0.778
        ]
      }
    },
    {
      "id": "chair_dining_four_back_no1",
      "label": "Chair",
      "category": "chair",
      "bounds": {
        "min": [
          1.497,
          10.07,
          0.099
        ],
        "max": [
          2.191,
          10.564,
          0.893
        ]
      }
    },
    {
      "id": "table_other_rect1",
      "label": "Table",
      "category": "table",
      "bounds": {
        "min": [
          0.931,
          -10.83,
          0.099
        ],
        "max": [
          1.539,
          -9.158,
          0.634
        ]
      }
    },
    {
      "id": "table_other_rect2",
      "label": "Table",
      "category": "table",
      "bounds": {
        "min": [
          -0.329,
          -16.86,
          0.099
        ],
        "max": [
          1.539,
          -16.373,
          0.654
        ]
      }
    }
  ],
  "windows_solar": [],
  "cameras": [],
  "analysis": {
    "coverage_pct": 0.0,
    "entry_points_covered": 0,
    "entry_points_total": 8,
    "blind_spots": [],
    "overlap_zones": 0,
    "total_cost_usd": 0.0,
    "lighting_risks": []
  },
  "_raw_rooms": [
    {
      "id": "room_0",
      "raw_label": "Other",
      "polygon": [
        [
          -3.9223607,
          -4.7474858
        ],
        [
          -3.6650456,
          -4.7474858
        ],
        [
          -0.6290283,
          -4.7474858
        ],
        [
          -0.6290283,
          -5.413675
        ],
        [
          1.5894965,
          -5.413675
        ],
        [
          3.97236,
          -5.413675
        ],
        [
          3.97236,
          -1.8795709
        ],
        [
          0.83083125,
          -1.8795709
        ],
        [
          -0.62902769,
          -1.8795697
        ],
        [
          -3.9223607,
          -1.8795697
        ]
      ],
      "center": [
        -0.303180354,
        -3.8001763599999996
      ],
      "size": [
        7.894720700000001,
        3.5341052999999993
      ],
      "area_m2": 25.706787145249763
    },
    {
      "id": "room_1",
      "raw_label": "Other",
      "polygon": [
        [
          -0.62902769,
          -1.8795697
        ],
        [
          0.83083125,
          -1.8795697
        ],
        [
          0.83083125,
          8.51157
        ],
        [
          -0.62902769,
          8.51157
        ]
      ],
      "center": [
        0.10090178,
        3.3160001500000003
      ],
      "size": [
        1.4598589400000002,
        10.3911397
      ],
      "area_m2": 15.16959818783392
    },
    {
      "id": "room_2",
      "raw_label": "Other",
      "polygon": [
        [
          -0.6290283,
          -15.390214
        ],
        [
          -0.6290283,
          -16.909955
        ],
        [
          1.5894965,
          -16.909955
        ],
        [
          1.5894965,
          -5.413675
        ],
        [
          -0.6290283,
          -5.413675
        ]
      ],
      "center": [
        0.25838162000000003,
        -12.0074948
      ],
      "size": [
        2.2185248,
        11.49628
      ],
      "area_m2": 25.504782287744007
    },
    {
      "id": "room_3",
      "raw_label": "Other",
      "polygon": [
        [
          -0.62902769,
          8.51157
        ],
        [
          0.83083125,
          8.51157
        ],
        [
          2.2488816,
          8.51157
        ],
        [
          2.2488816,
          14.733961
        ],
        [
          1.7005978,
          14.733961
        ],
        [
          -0.43167455,
          14.733961
        ],
        [
          -0.43167455,
          14.374497
        ],
        [
          -0.62902769,
          14.374497
        ]
      ],
      "center": [
        0.61347347125,
        12.310698375000001
      ],
      "size": [
        2.87790929,
        6.222391
      ],
      "area_m2": 17.836535515795426
    }
  ]
}